RWFileLock/__init__.py
RWFileLock/py.typed
RWFileLock/rw_file_lock.py
RWFileLock-0.2.2.dist-info/LICENSE
RWFileLock-0.2.2.dist-info/METADATA
RWFileLock-0.2.2.dist-info/WHEEL
RWFileLock-0.2.2.dist-info/top_level.txt
RWFileLock-0.2.2.dist-info/RECORD
