Metadata-Version: 2.1
Name: RWFileLock
Version: 0.2.2
Summary: Readers / writers file lock helper class
Home-page: https://github.com/inab/RWFileLock
Author: José M. Fernández <https://orcid.org/0000-0002-4806-5140>
Author-email: jose.m.fernandez@bsc.es
License: LGPLv2
Project-URL: Source, https://github.com/inab/RWFileLock
Project-URL: Bug Tracker, https://github.com/inab/RWFileLock/issues
Classifier: Programming Language :: Python :: 3
Classifier: Programming Language :: Python :: 3.7
Classifier: Programming Language :: Python :: 3.8
Classifier: Programming Language :: Python :: 3.9
Classifier: Programming Language :: Python :: 3.10
Classifier: Programming Language :: Python :: 3.11
Classifier: Programming Language :: Python :: 3.12
Classifier: License :: OSI Approved :: GNU Lesser General Public License v2 (LGPLv2)
Classifier: Operating System :: OS Independent
Requires-Python: >=3.7
License-File: LICENSE
